pharia_data_sdk/__init__.py
pharia_data_sdk/py.typed
pharia_data_sdk/connectors/__init__.py
pharia_data_sdk/connectors/base/json_serializable.py
pharia_data_sdk/connectors/data/__init__.py
pharia_data_sdk/connectors/data/data.py
pharia_data_sdk/connectors/data/exceptions.py
pharia_data_sdk/connectors/data/models.py
pharia_data_sdk/connectors/document_index/__init__.py
pharia_data_sdk/connectors/document_index/document_index.py
pharia_data_sdk/connectors/retrievers/__init__.py
pharia_data_sdk/connectors/retrievers/base_retriever.py
pharia_data_sdk/connectors/retrievers/document_index_retriever.py
pharia_data_sdk/connectors/retrievers/hybrid_qdrant_in_memory_retriever.py
pharia_data_sdk/connectors/retrievers/qdrant_in_memory_retriever.py
pharia_data_sdk-0.1.4.dist-info/METADATA
pharia_data_sdk-0.1.4.dist-info/WHEEL
pharia_data_sdk-0.1.4.dist-info/licenses/LICENSE
pharia_data_sdk-0.1.4.dist-info/licenses/NOTICE.md
pharia_data_sdk-0.1.4.dist-info/RECORD
