Metadata-Version: 2.4
Name: pharia-data-sdk
Version: 0.1.4
Project-URL: repository, https://github.com/Aleph-Alpha/pharia-data-sdk.git
Author-email: Aleph Alpha Engineering <engineering@aleph-alpha.com>
License-File: LICENSE
License-File: NOTICE.md
Requires-Python: <3.13,>=3.10
Requires-Dist: aleph-alpha-client<11.0.0,>=10.2.2
Requires-Dist: pharia-inference-sdk>=0.1.5
Requires-Dist: pydantic>=2.0.0
Requires-Dist: qdrant-client[fastembed]>=1.14.3
Requires-Dist: semantic-text-splitter>=0.5.0
